MANIFEST.in
README.rst
ravenclient.py
setup.py
ravenclient.egg-info/PKG-INFO
ravenclient.egg-info/SOURCES.txt
ravenclient.egg-info/dependency_links.txt
ravenclient.egg-info/requires.txt
ravenclient.egg-info/top_level.txt