Metadata-Version: 1.1
Name: ravenclient
Version: 0.7.0
Summary: A python requests adapter to automatically login to the Cambridge University Raven Login
Home-page: https://github.com/eric-wieser/raven-client
Author: Eric Wieser
Author-email: wieser.eric+raven@gmail.com
License: UNKNOWN
Download-URL: https://github.com/eric-wieser/raven-client/tarball/v0.7.0
Keywords: authentication,requests,raven
Platform: UNKNOWN
Classifier: License :: OSI Approved :: MIT License
Classifier: Programming Language :: Python :: 2.7
Classifier: Programming Language :: Python :: 3.5
Classifier: Intended Audience :: Developers
